MANIFEST.in
NOTICE.md
README.md
setup.py
Helix/__init__.py
Helix/helix.py
Helix/version.py
Helix_Engine_TEST.egg-info/PKG-INFO
Helix_Engine_TEST.egg-info/SOURCES.txt
Helix_Engine_TEST.egg-info/dependency_links.txt
Helix_Engine_TEST.egg-info/requires.txt
Helix_Engine_TEST.egg-info/top_level.txt
tests/test-init.py