Metadata-Version: 2.1
Name: Helix-Engine-TEST
Version: 1.0.0
Summary: Helix [ more than developers ]
Home-page: https://github.com/TheDotBat/Helix
Author: Izaiyah Stokes
Author-email: setoichi.dev@gmail.com
License: Apache-2.0
Classifier: Development Status :: 4 - Beta
Classifier: Intended Audience :: Developers
Classifier: License :: OSI Approved :: Apache Software License
Classifier: Programming Language :: Python :: 3
Classifier: Programming Language :: Python :: 3.10
Classifier: Programming Language :: Python :: 3.11
Classifier: Programming Language :: Python :: 3.12
Classifier: Topic :: Software Development :: Libraries :: pygame
Classifier: Operating System :: Microsoft :: Windows :: Windows 11
License-File: NOTICE.md
Requires-Dist: Numpy
Requires-Dist: PyGLM
Requires-Dist: pygame-ce
Requires-Dist: Numba
Requires-Dist: ModernGL
Requires-Dist: OpenSimplex
